mindlessgen/__init__.py
mindlessgen/__main__.py
mindlessgen/__version__.py
mindlessgen/cli/__init__.py
mindlessgen/cli/cli_parser.py
mindlessgen/cli/entrypoint.py
mindlessgen/data/__init__.py
mindlessgen/data/constants.py
mindlessgen/data/parameters.py
mindlessgen/generator/__init__.py
mindlessgen/generator/main.py
mindlessgen/molecules/__init__.py
mindlessgen/molecules/generate_molecule.py
mindlessgen/molecules/miscellaneous.py
mindlessgen/molecules/molecule.py
mindlessgen/molecules/postprocess.py
mindlessgen/molecules/refinement.py
mindlessgen/prog/__init__.py
mindlessgen/prog/config.py
mindlessgen/prog/parallel.py
mindlessgen/qm/__init__.py
mindlessgen/qm/base.py
mindlessgen/qm/gxtb.py
mindlessgen/qm/orca.py
mindlessgen/qm/tm.py
mindlessgen/qm/xtb.py
mindlessgen/symmetrization/__init__.py
mindlessgen/symmetrization/base.py
mindlessgen/symmetrization/inversion.py
mindlessgen/symmetrization/mirror.py
mindlessgen/symmetrization/rotation.py
mindlessgen-0.6.0.dist-info/licenses/LICENSE
mindlessgen-0.6.0.dist-info/METADATA
mindlessgen-0.6.0.dist-info/WHEEL
mindlessgen-0.6.0.dist-info/entry_points.txt
mindlessgen-0.6.0.dist-info/top_level.txt
mindlessgen-0.6.0.dist-info/RECORD
