Metadata-Version: 2.4
Name: mindlessgen
Version: 0.6.0
Summary: Mindless Molecule Generator
Author-email: Marcel Müller <marcel.mueller@thch.uni-bonn.de>, Jonathan Schöps <s6jtscho@uni-bonn.de>
Project-URL: GitHub, https://github.com/grimme-lab/MindlessGen
Project-URL: Changelog, https://github.com/grimme-lab/MindlessGen/blob/main/CHANGELOG.md
Project-URL: Issues, https://github.com/grimme-lab/MindlessGen/issues
Classifier: License :: OSI Approved :: Apache Software License
Classifier: Programming Language :: Python :: 3 :: Only
Classifier: Programming Language :: Python :: 3.10
Classifier: Programming Language :: Python :: 3.11
Classifier: Programming Language :: Python :: 3.12
Classifier: Programming Language :: Python :: 3.13
Classifier: Topic :: Scientific/Engineering
Classifier: Typing :: Typed
Requires-Python: >=3.10
License-File: LICENSE
Requires-Dist: numpy
Requires-Dist: networkx
Requires-Dist: toml
Requires-Dist: tqdm
Provides-Extra: dev
Requires-Dist: ruff==0.5.7; extra == "dev"
Requires-Dist: mypy; extra == "dev"
Requires-Dist: covdefaults; extra == "dev"
Requires-Dist: coverage; extra == "dev"
Requires-Dist: pre-commit; extra == "dev"
Requires-Dist: pytest; extra == "dev"
Requires-Dist: tox; extra == "dev"
Requires-Dist: setuptools_scm>=8; extra == "dev"
Requires-Dist: types-toml; extra == "dev"
Requires-Dist: types-tqdm; extra == "dev"
Dynamic: license-file
